README.rst
setup.py
remote_postgres/__init__.py
remote_postgres.egg-info/PKG-INFO
remote_postgres.egg-info/SOURCES.txt
remote_postgres.egg-info/dependency_links.txt
remote_postgres.egg-info/requires.txt
remote_postgres.egg-info/top_level.txt