Metadata-Version: 2.1
Name: remote-postgres
Version: 1.2.5
Summary: RemotePostgres is a way to easily access a remote Postgres database and perform queries
Home-page: https://github.com/vbalasu/RemotePostgres
Author: Vijay Balasubramaniam
Author-email: vbalasu@gmail.com
License: MIT
Download-URL: https://github.com/vbalasu/RemotePostgres/archive/v1.2.tar.gz
Keywords: postgres,remote
Platform: UNKNOWN
Classifier: Development Status :: 5 - Production/Stable
Classifier: Intended Audience :: Developers
Classifier: Topic :: Software Development :: Build Tools
Classifier: License :: OSI Approved :: MIT License
Classifier: Programming Language :: Python :: 3
Classifier: Programming Language :: Python :: 3.4
Classifier: Programming Language :: Python :: 3.5
Classifier: Programming Language :: Python :: 3.6
Classifier: Programming Language :: Python :: 3.7
